{"2": [{"lesson": "2", "group": "2.S celá", "room": "23", "subject": "FY", "subject_text": "Fyzika", "teacher": "", "teacher_text": "", "change_info": "", "theme": "", "type": "atom", "absencetext": "", "has_absent": "false", "absent_info_text": "", "removed_info": ""}], "3": [{"lesson": "3", "group": "1.EE celá", "room": "52", "subject": "FY", "subject_text": "Fyzika", "teacher": "", "teacher_text": "", "change_info": "", "theme": "", "type": "atom", "absencetext": "", "has_absent": "false", "absent_info_text": "", "removed_info": ""}], "4": [{"lesson": "4", "group": "1.EE celá", "room": "52", "subject": "MA", "subject_text": "Matematika", "teacher": "", "teacher_text": "", "change_info": "", "theme": "", "type": "atom", "absencetext": "", "has_absent": "false", "absent_info_text": "", "removed_info": ""}], "6": [{"lesson": "6", "group": "2.EM celá", "room": "13", "subject": "MA", "subject_text": "Matematika", "teacher": "", "teacher_text": "", "change_info": "", "theme": "", "type": "atom", "absencetext": "", "has_absent": "false", "absent_info_text": "", "removed_info": ""}], "7": [{"lesson": "7", "group": "3.EB celá", "room": "43", "subject": "MA", "subject_text": "Matematika", "teacher": "", "teacher_text": "", "change_info": "", "theme": "", "type": "atom", "absencetext": "", "has_absent": "false", "absent_info_text": "", "removed_info": ""}], "12": [{"lesson": "1", "group": "3.EB celá", "room": "43", "subject": "MA", "subject_text": "Matematika", "teacher": "", "teacher_text": "", "change_info": "", "theme": "", "type": "atom", "absencetext": "", "has_absent": "false", "absent_info_text": "", "removed_info": ""}], "13": [{"lesson": "2", "group": "1.EE celá", "room": "52", "subject": "MA", "subject_text": "Matematika", "teacher": "", "teacher_text": "", "change_info": "", "theme": "", "type": "atom", "absencetext": "", "has_absent": "false", "absent_info_text": "", "removed_info": ""}], "14": [{"lesson": "3", "group": "2.EM 1", "room": "32", "subject": "MA", "subject_text": "Matematika", "teacher": "", "teacher_text": "", "change_info": "", "theme": "", "type": "atom", "absencetext": "", "has_absent": "false", "absent_info_text": "", "removed_info": ""}], "15": [{"lesson": "4", "group": "2.EM 2", "room": "50", "subject": "MA", "subject_text": "Matematika", "teacher": "", "teacher_text": "", "change_info": "", "theme": "", "type": "atom", "absencetext": "", "has_absent": "false", "absent_info_text": "", "removed_info": ""}], "16": [{"lesson": "5", "group": "3.SA celá", "room": "29", "subject": "MA", "subject_text": "Matematika", "teacher": "", "teacher_text": "", "change_info": "", "theme": "", "type": "atom", "absencetext": "", "has_absent": "false", "absent_info_text": "", "removed_info": ""}], "23": [{"lesson": "1", "group": "4.EA celá", "room": "29", "subject": "MA", "subject_text": "Matematika", "teacher": "", "teacher_text": "", "change_info": "", "theme": "", "type": "atom", "absencetext": "", "has_absent": "false", "absent_info_text": "", "removed_info": ""}], "24": [{"lesson": "2", "group": "1.EE 1", "room": "52", "subject": "MA", "subject_text": "Matematika", "teacher": "", "teacher_text": "", "change_info": "", "theme": "", "type": "atom", "absencetext": "", "has_absent": "false", "absent_info_text": "", "removed_info": ""}], "25": [{"lesson": "3", "group": "1.EE 2", "room": "52", "subject": "MA", "subject_text": "Matematika", "teacher": "", "teacher_text": "", "change_info": "", "theme": "", "type": "atom", "absencetext": "", "has_absent": "false", "absent_info_text": "", "removed_info": ""}], "26": [{"lesson": "4", "group": "4.EA 1", "room": "29", "subject": "MA", "subject_text": "Matematika", "teacher": "", "teacher_text": "", "change_info": "", "theme": "", "type": "atom", "absencetext": "", "has_absent": "false", "absent_info_text": "", "removed_info": ""}], "27": [{"lesson": "5", "group": "4.EA 2", "room": "29", "subject": "MA", "subject_text": "Matematika", "teacher": "", "teacher_text": "", "change_info": "", "theme": "", "type": "atom", "absencetext": "", "has_absent": "false", "absent_info_text": "", "removed_info": ""}], "29": [{"lesson": "7", "group": "1.EE celá", "room": "52", "subject": "FY", "subject_text": "Fyzika", "teacher": "", "teacher_text": "", "change_info": "", "theme": "", "type": "atom", "absencetext": "", "has_absent": "false", "absent_info_text": "", "removed_info": ""}], "34": [{"lesson": "1", "group": "1.EE celá", "room": "52", "subject": "MA", "subject_text": "Matematika", "teacher": "", "teacher_text": "", "change_info": "", "theme": "", "type": "atom", "absencetext": "", "has_absent": "false", "absent_info_text": "", "removed_info": ""}], "35": [{"lesson": "2", "group": "3.SA celá", "room": "11", "subject": "MA", "subject_text": "Matematika", "teacher": "", "teacher_text": "", "change_info": "", "theme": "", "type": "atom", "absencetext": "", "has_absent": "false", "absent_info_text": "", "removed_info": ""}], "36": [{"lesson": "3", "group": "3.EB 1", "room": "43", "subject": "MA", "subject_text": "Matematika", "teacher": "", "teacher_text": "", "change_info": "", "theme": "", "type": "atom", "absencetext": "", "has_absent": "false", "absent_info_text": "", "removed_info": ""}], "37": [{"lesson": "4", "group": "3.EB 2", "room": "43", "subject": "MA", "subject_text": "Matematika", "teacher": "", "teacher_text": "", "change_info": "", "theme": "", "type": "atom", "absencetext": "", "has_absent": "false", "absent_info_text": "", "removed_info": ""}], "39": [{"lesson": "6", "group": "1.EE 1", "room": "15", "subject": "L: FY", "subject_text": "Fyzika", "teacher": "", "teacher_text": "", "change_info": "", "theme": "", "type": "atom", "absencetext": "", "has_absent": "false", "absent_info_text": "", "removed_info": ""}, {"lesson": "6", "group": "1.EE 2", "room": "15", "subject": "S: FY", "subject_text": "Fyzika", "teacher": "", "teacher_text": "", "change_info": "", "theme": "", "type": "atom", "absencetext": "", "has_absent": "false", "absent_info_text": "", "removed_info": ""}], "40": [{"lesson": "7", "group": "1.EE 1", "room": "15", "subject": "L: FY", "subject_text": "Fyzika", "teacher": "", "teacher_text": "", "change_info": "", "theme": "", "type": "atom", "absencetext": "", "has_absent": "false", "absent_info_text": "", "removed_info": ""}, {"lesson": "7", "group": "1.EE 2", "room": "15", "subject": "S: FY", "subject_text": "Fyzika", "teacher": "", "teacher_text": "", "change_info": "", "theme": "", "type": "atom", "absencetext": "", "has_absent": "false", "absent_info_text": "", "removed_info": ""}], "45": [{"lesson": "1", "group": "3.SA 1", "room": "11", "subject": "MA", "subject_text": "Matematika", "teacher": "", "teacher_text": "", "change_info": "", "theme": "", "type": "atom", "absencetext": "", "has_absent": "false", "absent_info_text": "", "removed_info": ""}], "46": [{"lesson": "2", "group": "2.EM celá", "room": "50", "subject": "MA", "subject_text": "Matematika", "teacher": "", "teacher_text": "", "change_info": "", "theme": "", "type": "atom", "absencetext": "", "has_absent": "false", "absent_info_text": "", "removed_info": ""}], "47": [{"lesson": "3", "group": "3.SA 2", "room": "41", "subject": "MA", "subject_text": "Matematika", "teacher": "", "teacher_text": "", "change_info": "", "theme": "", "type": "atom", "absencetext": "", "has_absent": "false", "absent_info_text": "", "removed_info": ""}], "48": [{"lesson": "4", "group": "2.S celá", "room": "23", "subject": "FY", "subject_text": "Fyzika", "teacher": "", "teacher_text": "", "change_info": "", "theme": "", "type": "atom", "absencetext": "", "has_absent": "false", "absent_info_text": "", "removed_info": ""}], "49": [{"lesson": "5", "group": "4.EA celá", "room": "29", "subject": "MA", "subject_text": "Matematika", "teacher": "", "teacher_text": "", "change_info": "", "theme": "", "type": "atom", "absencetext": "", "has_absent": "false", "absent_info_text": "", "removed_info": ""}]}