{"2": [{"lesson": "", "group": "", "room": "", "subject": "", "subject_text": "", "teacher": "", "teacher_text": "", "change_info": "", "theme": "", "type": "removed", "absencetext": "", "has_absent": "false", "absent_info_text": "", "removed_info": "Absence třídy (3.SB, ST)"}], "3": [{"lesson": "", "group": "", "room": "", "subject": "", "subject_text": "", "teacher": "", "teacher_text": "", "change_info": "", "theme": "", "type": "removed", "absencetext": "", "has_absent": "false", "absent_info_text": "", "removed_info": "Absence třídy (3.SB, ST)"}], "5": [{"lesson": "", "group": "", "room": "", "subject": "", "subject_text": "", "teacher": "", "teacher_text": "", "change_info": "", "theme": "", "type": "removed", "absencetext": "", "has_absent": "false", "absent_info_text": "", "removed_info": "Vyjmuto z rozvrhu (4.SA, ST)"}], "6": [{"lesson": "", "group": "", "room": "", "subject": "", "subject_text": "", "teacher": "", "teacher_text": "", "change_info": "", "theme": "", "type": "removed", "absencetext": "", "has_absent": "false", "absent_info_text": "", "removed_info": "Vyjmuto z rozvrhu (4.SA, ST)"}], "8": [{"lesson": "", "group": "", "room": "", "subject": "", "subject_text": "", "teacher": "", "teacher_text": "", "change_info": "", "theme": "", "type": "removed", "absencetext": "", "has_absent": "false", "absent_info_text": "", "removed_info": "Vyjmuto z rozvrhu (4.SA(1), STc)"}], "9": [{"lesson": "", "group": "", "room": "", "subject": "", "subject_text": "", "teacher": "", "teacher_text": "", "change_info": "", "theme": "", "type": "removed", "absencetext": "", "has_absent": "false", "absent_info_text": "", "removed_info": "Vyjmuto z rozvrhu (4.SA(1), STc)"}], "36": [{"lesson": "", "group": "", "room": "", "subject": "", "subject_text": "", "teacher": "", "teacher_text": "", "change_info": "", "theme": "", "type": "removed", "absencetext": "", "has_absent": "false", "absent_info_text": "", "removed_info": "Absence třídy (3.SB, ST)"}], "48": [{"lesson": "4", "group": "4.SA celá", "room": "41", "subject": "ST", "subject_text": "Strojírenská technologie", "teacher": "", "teacher_text": "", "change_info": "", "theme": "", "type": "atom", "absencetext": "", "has_absent": "false", "absent_info_text": "", "removed_info": ""}], "49": [{"lesson": "5", "group": "4.SA 2", "room": "41", "subject": "STc", "subject_text": "Strojírenská technol. cvičení", "teacher": "", "teacher_text": "", "change_info": "", "theme": "", "type": "atom", "absencetext": "", "has_absent": "false", "absent_info_text": "", "removed_info": ""}], "50": [{"lesson": "6", "group": "4.SA 2", "room": "41", "subject": "STc", "subject_text": "Strojírenská technol. cvičení", "teacher": "", "teacher_text": "", "change_info": "", "theme": "", "type": "atom", "absencetext": "", "has_absent": "false", "absent_info_text": "", "removed_info": ""}]}