{"1": [{"lesson": "1", "group": "", "room": "23", "subject": "CL", "subject_text": "Český jazyk a literatura", "teacher": "Kv", "teacher_text": "Mgr. Mirka Kováříková", "change_info": "", "theme": "Český realismus a naturalismus", "type": "atom", "absencetext": "", "has_absent": "false", "absent_info_text": "", "removed_info": ""}], "2": [{"lesson": "2", "group": "", "room": "23", "subject": "FY", "subject_text": "Fyzika", "teacher": "Pl", "teacher_text": "Mgr. Jiří Ploch", "change_info": "", "theme": "Optika - úvod", "type": "atom", "absencetext": "", "has_absent": "false", "absent_info_text": "", "removed_info": ""}], "3": [{"lesson": "3", "group": "1", "room": "41", "subject": "AJ", "subject_text": "Anglický jazyk", "teacher": "Ro", "teacher_text": "Mgr. Tomáš Rolínek", "change_info": "", "theme": "Příprava na Unit test 7", "type": "atom", "absencetext": "", "has_absent": "false", "absent_info_text": "", "removed_info": ""}, {"lesson": "3", "group": "2", "room": "23", "subject": "AJ", "subject_text": "Anglický jazyk", "teacher": "Má", "teacher_text": "Mgr. Daniela Marková", "change_info": "", "theme": "Review before unit 7", "type": "atom", "absencetext": "", "has_absent": "false", "absent_info_text": "", "removed_info": ""}], "4": [{"lesson": "4", "group": "1", "room": "42", "subject": "IT", "subject_text": "Informační technologie", "teacher": "Rů", "teacher_text": "Ing. Zdeněk Růžička", "change_info": "", "theme": "Závěrečná práce - Excel", "type": "atom", "absencetext": "", "has_absent": "false", "absent_info_text": "", "removed_info": ""}, {"lesson": "4", "group": "2", "room": "75", "subject": "IT", "subject_text": "Informační technologie", "teacher": "Pt", "teacher_text": "Bc. Jan Petrásek", "change_info": "", "theme": "Aktivní prvky sítě", "type": "atom", "absencetext": "", "has_absent": "false", "absent_info_text": "", "removed_info": ""}], "5": [{"lesson": "5", "group": "1", "room": "42", "subject": "IT", "subject_text": "Informační technologie", "teacher": "Rů", "teacher_text": "Ing. Zdeněk Růžička", "change_info": "", "theme": "Závěrečná práce - Excel", "type": "atom", "absencetext": "", "has_absent": "false", "absent_info_text": "", "removed_info": ""}, {"lesson": "5", "group": "2", "room": "75", "subject": "IT", "subject_text": "Informační technologie", "teacher": "Pt", "teacher_text": "Bc. Jan Petrásek", "change_info": "", "theme": "ISO/OSI", "type": "atom", "absencetext": "", "has_absent": "false", "absent_info_text": "", "removed_info": ""}], "6": [{"lesson": "6", "group": "", "room": "23", "subject": "MA", "subject_text": "Matematika", "teacher": "Ml", "teacher_text": "Mgr. Michaela Malíková", "change_info": "", "theme": "Procvičování objemy a povrchy", "type": "atom", "absencetext": "", "has_absent": "false", "absent_info_text": "", "removed_info": ""}], "12": [{"lesson": "1", "group": "", "room": "23", "subject": "CL", "subject_text": "Český jazyk a literatura", "teacher": "Kv", "teacher_text": "Mgr. Mirka Kováříková", "change_info": "", "theme": "Český realismus a naturalismus", "type": "atom", "absencetext": "", "has_absent": "false", "absent_info_text": "", "removed_info": ""}], "13": [{"lesson": "2", "group": "1", "room": "35", "subject": "TV", "subject_text": "Tělesná výchova", "teacher": "Bi", "teacher_text": "Mgr. Tomáš Bican", "change_info": "", "theme": "Lavičky", "type": "atom", "absencetext": "", "has_absent": "false", "absent_info_text": "", "removed_info": ""}, {"lesson": "2", "group": "2", "room": "", "subject": "TV", "subject_text": "Tělesná výchova", "teacher": "Ma", "teacher_text": "Mgr Radek Mach", "change_info": "", "theme": "Lavičky", "type": "atom", "absencetext": "", "has_absent": "false", "absent_info_text": "", "removed_info": ""}], "14": [{"lesson": "3", "group": "1", "room": "35", "subject": "TV", "subject_text": "Tělesná výchova", "teacher": "Bi", "teacher_text": "Mgr. Tomáš Bican", "change_info": "", "theme": "Míčové hry", "type": "atom", "absencetext": "", "has_absent": "false", "absent_info_text": "", "removed_info": ""}, {"lesson": "3", "group": "2", "room": "", "subject": "TV", "subject_text": "Tělesná výchova", "teacher": "Ma", "teacher_text": "Mgr Radek Mach", "change_info": "", "theme": "Míčové hry", "type": "atom", "absencetext": "", "has_absent": "false", "absent_info_text": "", "removed_info": ""}], "15": [{"lesson": "4", "group": "P1", "room": "24", "subject": "KPP", "subject_text": "Konstruování pomocí počítačů", "teacher": "Čk", "teacher_text": "Ing. Vilém Čejka", "change_info": "", "theme": "Kusovník sestavy kladky", "type": "atom", "absencetext": "", "has_absent": "false", "absent_info_text": "", "removed_info": ""}, {"lesson": "4", "group": "P2", "room": "42", "subject": "KPP", "subject_text": "Konstruování pomocí počítačů", "teacher": "St", "teacher_text": "Ing. Stanislav Strnad", "change_info": "", "theme": "Spojení profilů", "type": "atom", "absencetext": "", "has_absent": "false", "absent_info_text": "", "removed_info": ""}, {"lesson": "4", "group": "P3", "room": "75", "subject": "KPP", "subject_text": "Konstruování pomocí počítačů", "teacher": "Ta", "teacher_text": "Mgr. Aleš Trojan", "change_info": "", "theme": "Sestava kladky", "type": "atom", "absencetext": "", "has_absent": "false", "absent_info_text": "", "removed_info": ""}], "16": [{"lesson": "5", "group": "P1", "room": "24", "subject": "KPP", "subject_text": "Konstruování pomocí počítačů", "teacher": "Čk", "teacher_text": "Ing. Vilém Čejka", "change_info": "", "theme": "Výrobní výkres kladky", "type": "atom", "absencetext": "", "has_absent": "false", "absent_info_text": "", "removed_info": ""}, {"lesson": "5", "group": "P2", "room": "42", "subject": "KPP", "subject_text": "Konstruování pomocí počítačů", "teacher": "St", "teacher_text": "Ing. Stanislav Strnad", "change_info": "", "theme": "Tažení po křivce", "type": "atom", "absencetext": "", "has_absent": "false", "absent_info_text": "", "removed_info": ""}, {"lesson": "5", "group": "P3", "room": "75", "subject": "KPP", "subject_text": "Konstruování pomocí počítačů", "teacher": "Ta", "teacher_text": "Mgr. Aleš Trojan", "change_info": "", "theme": "Editace kladky", "type": "atom", "absencetext": "", "has_absent": "false", "absent_info_text": "", "removed_info": ""}], "17": [{"lesson": "6", "group": "1", "room": "41", "subject": "AJ", "subject_text": "Anglický jazyk", "teacher": "Ro", "teacher_text": "Mgr. Tomáš Rolínek", "change_info": "", "theme": "", "type": "atom", "absencetext": "", "has_absent": "false", "absent_info_text": "", "removed_info": ""}, {"lesson": "6", "group": "2", "room": "23", "subject": "AJ", "subject_text": "Anglický jazyk", "teacher": "Má", "teacher_text": "Mgr. Daniela Marková", "change_info": "", "theme": "Unit 7 test", "type": "atom", "absencetext": "", "has_absent": "false", "absent_info_text": "", "removed_info": ""}], "19": [{"lesson": "8", "group": "2", "room": "25", "subject": "SSc", "subject_text": "Stavba a provoz str. cvičení", "teacher": "Kp", "teacher_text": "Ing. Petr Kroupa", "change_info": "", "theme": "Kontrola výpočtů, konzultace výkresů, vyplňování popisového pole.", "type": "atom", "absencetext": "", "has_absent": "false", "absent_info_text": "", "removed_info": ""}], "20": [{"lesson": "9", "group": "2", "room": "25", "subject": "SSc", "subject_text": "Stavba a provoz str. cvičení", "teacher": "Kp", "teacher_text": "Ing. Petr Kroupa", "change_info": "", "theme": "Kontrola výpočtů, konzultace výkresů, vyplňování popisového pole", "type": "atom", "absencetext": "", "has_absent": "false", "absent_info_text": "", "removed_info": ""}], "23": [{"lesson": "1", "group": "", "room": "23", "subject": "CL", "subject_text": "Český jazyk a literatura", "teacher": "Kv", "teacher_text": "Mgr. Mirka Kováříková", "change_info": "", "theme": "Májovci, ruchovci, lumírovci - písemka; tvarosloví", "type": "atom", "absencetext": "", "has_absent": "false", "absent_info_text": "", "removed_info": ""}], "24": [{"lesson": "2", "group": "", "room": "25", "subject": "ME", "subject_text": "Mechanika", "teacher": "Kp", "teacher_text": "Ing. Petr Kroupa", "change_info": "", "theme": "Řešení příkladů rovměrné přímočaré pohyby.", "type": "atom", "absencetext": "", "has_absent": "false", "absent_info_text": "", "removed_info": ""}], "25": [{"lesson": "3", "group": "", "room": "23", "subject": "EL", "subject_text": "Elektrotechnika", "teacher": "Su", "teacher_text": "Ing. Jaroslav Stuchlý", "change_info": "", "theme": "", "type": "atom", "absencetext": "", "has_absent": "false", "absent_info_text": "", "removed_info": ""}], "26": [{"lesson": "", "group": "", "room": "", "subject": "ŠA", "subject_text": "Školní akce", "teacher": "", "teacher_text": "", "change_info": "", "theme": "", "type": "absent", "absencetext": "", "has_absent": "false", "absent_info_text": "", "removed_info": ""}], "27": [{"lesson": "5", "group": "", "room": "23", "subject": "MA", "subject_text": "Matematika", "teacher": "Ml", "teacher_text": "Mgr. Michaela Malíková", "change_info": "", "theme": "", "type": "atom", "absencetext": "", "has_absent": "false", "absent_info_text": "", "removed_info": ""}], "28": [{"lesson": "6", "group": "", "room": "25", "subject": "SS", "subject_text": "Stavba a provoz strojů", "teacher": "Kp", "teacher_text": "Ing. Petr Kroupa", "change_info": "", "theme": "Výpočet kluzných ložisek. Mazání kluzných ložisek.", "type": "atom", "absencetext": "", "has_absent": "false", "absent_info_text": "", "removed_info": ""}]}