{"1": [{"lesson": "1", "group": "", "room": "23", "subject": "CL", "subject_text": "Český jazyk a literatura", "teacher": "Kv", "teacher_text": "Mgr. Mirka Kováříková", "change_info": "", "theme": "Májovci, ruchovci, lumírovci", "type": "atom", "absencetext": "", "has_absent": "false", "absent_info_text": "", "removed_info": ""}], "2": [{"lesson": "2", "group": "", "room": "23", "subject": "FY", "subject_text": "Fyzika", "teacher": "Pl", "teacher_text": "Mgr. Jiří Ploch", "change_info": "", "theme": "Zvuk a jeho vlastnosti", "type": "atom", "absencetext": "", "has_absent": "false", "absent_info_text": "", "removed_info": ""}], "3": [{"lesson": "3", "group": "1", "room": "41", "subject": "AJ", "subject_text": "Anglický jazyk", "teacher": "Ro", "teacher_text": "Mgr. Tomáš Rolínek", "change_info": "", "theme": "Practice Text SB 57/1,2,3", "type": "atom", "absencetext": "", "has_absent": "false", "absent_info_text": "", "removed_info": ""}, {"lesson": "3", "group": "2", "room": "23", "subject": "AJ", "subject_text": "Anglický jazyk", "teacher": "Má", "teacher_text": "Mgr. Daniela Marková", "change_info": "", "theme": "Writing a biography", "type": "atom", "absencetext": "", "has_absent": "false", "absent_info_text": "", "removed_info": ""}], "4": [{"lesson": "4", "group": "1", "room": "75", "subject": "IT", "subject_text": "Informační technologie", "teacher": "Pt", "teacher_text": "Bc. Jan Petrásek", "change_info": "", "theme": "Úvod do PC sítí", "type": "atom", "absencetext": "", "has_absent": "false", "absent_info_text": "", "removed_info": ""}, {"lesson": "4", "group": "2", "room": "42", "subject": "IT", "subject_text": "Informační technologie", "teacher": "Rů", "teacher_text": "Ing. Zdeněk Růžička", "change_info": "", "theme": "Excel - shrnutí", "type": "atom", "absencetext": "", "has_absent": "false", "absent_info_text": "", "removed_info": ""}], "5": [{"lesson": "5", "group": "1", "room": "75", "subject": "IT", "subject_text": "Informační technologie", "teacher": "Pt", "teacher_text": "Bc. Jan Petrásek", "change_info": "", "theme": "Úvod do PC sítí", "type": "atom", "absencetext": "", "has_absent": "false", "absent_info_text": "", "removed_info": ""}, {"lesson": "5", "group": "2", "room": "42", "subject": "IT", "subject_text": "Informační technologie", "teacher": "Rů", "teacher_text": "Ing. Zdeněk Růžička", "change_info": "", "theme": "HTML - úvod", "type": "atom", "absencetext": "", "has_absent": "false", "absent_info_text": "", "removed_info": ""}], "6": [{"lesson": "6", "group": "", "room": "23", "subject": "MA", "subject_text": "Matematika", "teacher": "Ml", "teacher_text": "Mgr. Michaela Malíková", "change_info": "", "theme": "Odchylky - procvičování", "type": "atom", "absencetext": "", "has_absent": "false", "absent_info_text": "", "removed_info": ""}], "12": [{"lesson": "1", "group": "", "room": "23", "subject": "CL", "subject_text": "Český jazyk a literatura", "teacher": "Kv", "teacher_text": "Mgr. Mirka Kováříková", "change_info": "", "theme": "Májovci, ruchovci, lumírovci; funkční styl administrativní - písemka", "type": "atom", "absencetext": "", "has_absent": "false", "absent_info_text": "", "removed_info": ""}], "13": [{"lesson": "2", "group": "1", "room": "35", "subject": "TV", "subject_text": "Tělesná výchova", "teacher": "Bi", "teacher_text": "Mgr. Tomáš Bican", "change_info": "", "theme": "Překážkové dráhy", "type": "atom", "absencetext": "", "has_absent": "false", "absent_info_text": "", "removed_info": ""}, {"lesson": "2", "group": "2", "room": "", "subject": "TV", "subject_text": "Tělesná výchova", "teacher": "Ma", "teacher_text": "Mgr Radek Mach", "change_info": "", "theme": "Překážkové dráhy", "type": "atom", "absencetext": "", "has_absent": "false", "absent_info_text": "", "removed_info": ""}], "14": [{"lesson": "3", "group": "1", "room": "35", "subject": "TV", "subject_text": "Tělesná výchova", "teacher": "Bi", "teacher_text": "Mgr. Tomáš Bican", "change_info": "", "theme": "Vybíjená", "type": "atom", "absencetext": "", "has_absent": "false", "absent_info_text": "", "removed_info": ""}, {"lesson": "3", "group": "2", "room": "", "subject": "TV", "subject_text": "Tělesná výchova", "teacher": "Ma", "teacher_text": "Mgr Radek Mach", "change_info": "", "theme": "Vybíjená", "type": "atom", "absencetext": "", "has_absent": "false", "absent_info_text": "", "removed_info": ""}], "15": [{"lesson": "4", "group": "P1", "room": "24", "subject": "KPP", "subject_text": "Konstruování pomocí počítačů", "teacher": "Čk", "teacher_text": "Ing. Vilém Čejka", "change_info": "", "theme": "Šroubový spoj", "type": "atom", "absencetext": "", "has_absent": "false", "absent_info_text": "", "removed_info": ""}, {"lesson": "4", "group": "P2", "room": "42", "subject": "KPP", "subject_text": "Konstruování pomocí počítačů", "teacher": "St", "teacher_text": "Ing. Stanislav Strnad", "change_info": "", "theme": "Sestava kladky", "type": "atom", "absencetext": "", "has_absent": "false", "absent_info_text": "", "removed_info": ""}, {"lesson": "4", "group": "P3", "room": "75", "subject": "KPP", "subject_text": "Konstruování pomocí počítačů", "teacher": "Ta", "teacher_text": "Mgr. Aleš Trojan", "change_info": "", "theme": "Sestava", "type": "atom", "absencetext": "", "has_absent": "false", "absent_info_text": "", "removed_info": ""}], "16": [{"lesson": "5", "group": "P1", "room": "24", "subject": "KPP", "subject_text": "Konstruování pomocí počítačů", "teacher": "Čk", "teacher_text": "Ing. Vilém Čejka", "change_info": "", "theme": "Závlačka parametricky", "type": "atom", "absencetext": "", "has_absent": "false", "absent_info_text": "", "removed_info": ""}, {"lesson": "5", "group": "P2", "room": "42", "subject": "KPP", "subject_text": "Konstruování pomocí počítačů", "teacher": "St", "teacher_text": "Ing. Stanislav Strnad", "change_info": "", "theme": "Sestava kladky", "type": "atom", "absencetext": "", "has_absent": "false", "absent_info_text": "", "removed_info": ""}, {"lesson": "5", "group": "P3", "room": "75", "subject": "KPP", "subject_text": "Konstruování pomocí počítačů", "teacher": "Ta", "teacher_text": "Mgr. Aleš Trojan", "change_info": "", "theme": "Sestava", "type": "atom", "absencetext": "", "has_absent": "false", "absent_info_text": "", "removed_info": ""}], "17": [{"lesson": "6", "group": "1", "room": "41", "subject": "AJ", "subject_text": "Anglický jazyk", "teacher": "Ro", "teacher_text": "Mgr. Tomáš Rolínek", "change_info": "", "theme": "SB60, Vocabulary SB57", "type": "atom", "absencetext": "", "has_absent": "false", "absent_info_text": "", "removed_info": ""}, {"lesson": "6", "group": "2", "room": "23", "subject": "AJ", "subject_text": "Anglický jazyk", "teacher": "Má", "teacher_text": "Mgr. Daniela Marková", "change_info": "", "theme": "Writing a biography", "type": "atom", "absencetext": "", "has_absent": "false", "absent_info_text": "", "removed_info": ""}], "19": [{"lesson": "8", "group": "1", "room": "25", "subject": "SSc", "subject_text": "Stavba a provoz str. cvičení", "teacher": "Kp", "teacher_text": "Ing. Petr Kroupa", "change_info": "", "theme": "Konzultace výsledků výpočto a podkladových výkresů - uložení kladky.", "type": "atom", "absencetext": "", "has_absent": "false", "absent_info_text": "", "removed_info": ""}], "20": [{"lesson": "9", "group": "1", "room": "25", "subject": "SSc", "subject_text": "Stavba a provoz str. cvičení", "teacher": "Kp", "teacher_text": "Ing. Petr Kroupa", "change_info": "", "theme": "Konzultace výsledků výpočto a podkladových výkresů - uložení kladky.", "type": "atom", "absencetext": "", "has_absent": "false", "absent_info_text": "", "removed_info": ""}], "23": [{"lesson": "1", "group": "", "room": "23", "subject": "CL", "subject_text": "Český jazyk a literatura", "teacher": "Kv", "teacher_text": "Mgr. Mirka Kováříková", "change_info": "", "theme": "Strukturovaný životopis - opakování; český realismus a naturalismus - okrajoví autoři", "type": "atom", "absencetext": "", "has_absent": "false", "absent_info_text": "", "removed_info": ""}], "24": [{"lesson": "2", "group": "", "room": "25", "subject": "ME", "subject_text": "Mechanika", "teacher": "Kp", "teacher_text": "Ing. Petr Kroupa", "change_info": "", "theme": "Zjednodušený tvar Smithova diagramu. Konstrukce.", "type": "atom", "absencetext": "", "has_absent": "false", "absent_info_text": "", "removed_info": ""}], "25": [{"lesson": "3", "group": "", "room": "23", "subject": "EL", "subject_text": "Elektrotechnika", "teacher": "Su", "teacher_text": "Ing. Jaroslav Stuchlý", "change_info": "", "theme": "Základy polovodičů, PN přechod, přechod polovodič-kov, polovodičová dioda", "type": "atom", "absencetext": "", "has_absent": "false", "absent_info_text": "", "removed_info": ""}], "26": [{"lesson": "", "group": "", "room": "", "subject": "ŠA", "subject_text": "Školní akce", "teacher": "", "teacher_text": "", "change_info": "", "theme": "", "type": "absent", "absencetext": "", "has_absent": "false", "absent_info_text": "", "removed_info": ""}], "27": [{"lesson": "5", "group": "", "room": "23", "subject": "MA", "subject_text": "Matematika", "teacher": "Ml", "teacher_text": "Mgr. Michaela Malíková", "change_info": "", "theme": "Opakování na test", "type": "atom", "absencetext": "", "has_absent": "false", "absent_info_text": "", "removed_info": ""}], "28": [{"lesson": "6", "group": "", "room": "25", "subject": "SS", "subject_text": "Stavba a provoz strojů", "teacher": "Kp", "teacher_text": "Ing. Petr Kroupa", "change_info": "", "theme": "Hřídele - základní rozdělení. Nosné hřídele.", "type": "atom", "absencetext": "", "has_absent": "false", "absent_info_text": "", "removed_info": ""}], "33": [{"lesson": "0", "group": "", "room": "23", "subject": "EL", "subject_text": "Elektrotechnika", "teacher": "Su", "teacher_text": "Ing. Jaroslav Stuchlý", "change_info": "", "theme": "Základy polovodičů - bipolární a unipolární tranzistor", "type": "atom", "absencetext": "", "has_absent": "false", "absent_info_text": "", "removed_info": ""}], "34": [{"lesson": "1", "group": "", "room": "25", "subject": "SS", "subject_text": "Stavba a provoz strojů", "teacher": "Kp", "teacher_text": "Ing. Petr Kroupa", "change_info": "", "theme": "Hybné hřídele - druhy, tok energie, namáhání a výpočet.", "type": "atom", "absencetext": "", "has_absent": "false", "absent_info_text": "", "removed_info": ""}], "35": [{"lesson": "2", "group": "1", "room": "59", "subject": "AJ", "subject_text": "Anglický jazyk", "teacher": "Ro", "teacher_text": "Mgr. Tomáš Rolínek", "change_info": "", "theme": "Worksheets - příprava na test Unit 7", "type": "atom", "absencetext": "", "has_absent": "false", "absent_info_text": "", "removed_info": ""}, {"lesson": "2", "group": "2", "room": "23", "subject": "MA", "subject_text": "Matematika", "teacher": "Ml", "teacher_text": "Mgr. Michaela Malíková", "change_info": "", "theme": "Test", "type": "atom", "absencetext": "", "has_absent": "false", "absent_info_text": "", "removed_info": ""}], "36": [{"lesson": "3", "group": "2", "room": "60", "subject": "AJ", "subject_text": "Anglický jazyk", "teacher": "Má", "teacher_text": "Mgr. Daniela Marková", "change_info": "", "theme": "Listening WB: Till death us do part", "type": "atom", "absencetext": "", "has_absent": "false", "absent_info_text": "", "removed_info": ""}, {"lesson": "3", "group": "1", "room": "23", "subject": "MA", "subject_text": "Matematika", "teacher": "Ml", "teacher_text": "Mgr. Michaela Malíková", "change_info": "", "theme": "Test", "type": "atom", "absencetext": "", "has_absent": "false", "absent_info_text": "", "removed_info": ""}], "37": [{"lesson": "4", "group": "", "room": "23", "subject": "ME", "subject_text": "Mechanika", "teacher": "Kp", "teacher_text": "Ing. Petr Kroupa", "change_info": "", "theme": "Tvarová pevnost.", "type": "atom", "absencetext": "", "has_absent": "false", "absent_info_text": "", "removed_info": ""}], "39": [{"lesson": "6", "group": "PD1", "room": "D13", "subject": "PRA", "subject_text": "Praxe", "teacher": "Sr", "teacher_text": "Stanislav Stropek", "change_info": "", "theme": "Frézování šikmých ploch", "type": "atom", "absencetext": "", "has_absent": "false", "absent_info_text": "", "removed_info": ""}, {"lesson": "6", "group": "PD2", "room": "D16", "subject": "PRA", "subject_text": "Praxe", "teacher": "La", "teacher_text": "Mgr. Ivan Lavička", "change_info": "", "theme": "Metoda 111 (MMA) - BOZP, svařovací zdroje, přídavné materiály, parametry, příprava materiálu před svařováním a polohy", "type": "atom", "absencetext": "", "has_absent": "false", "absent_info_text": "", "removed_info": ""}, {"lesson": "6", "group": "PD3", "room": "D25", "subject": "PRA", "subject_text": "Praxe", "teacher": "Ra", "teacher_text": "Petr Rákos", "change_info": "", "theme": "Zásuvky 400V rozdělení", "type": "atom", "absencetext": "", "has_absent": "false", "absent_info_text": "", "removed_info": ""}, {"lesson": "6", "group": "PD4", "room": "D14", "subject": "PRA", "subject_text": "Praxe", "teacher": "Vd", "teacher_text": "Mgr. Michal Vondrášek", "change_info": "", "theme": "Výroba zívitů", "type": "atom", "absencetext": "", "has_absent": "false", "absent_info_text": "", "removed_info": ""}], "40": [{"lesson": "7", "group": "PD1", "room": "D13", "subject": "PRA", "subject_text": "Praxe", "teacher": "Sr", "teacher_text": "Stanislav Stropek", "change_info": "", "theme": "Frézování šikmých ploch", "type": "atom", "absencetext": "", "has_absent": "false", "absent_info_text": "", "removed_info": ""}, {"lesson": "7", "group": "PD2", "room": "D16", "subject": "PRA", "subject_text": "Praxe", "teacher": "La", "teacher_text": "Mgr. Ivan Lavička", "change_info": "", "theme": "Metoda 111 (MMA) - BOZP, svařovací zdroje, přídavné materiály, parametry, příprava materiálu před svařováním a polohy", "type": "atom", "absencetext": "", "has_absent": "false", "absent_info_text": "", "removed_info": ""}, {"lesson": "7", "group": "PD3", "room": "D25", "subject": "PRA", "subject_text": "Praxe", "teacher": "Ra", "teacher_text": "Petr Rákos", "change_info": "", "theme": "Zásuvky 400V zapoování", "type": "atom", "absencetext": "", "has_absent": "false", "absent_info_text": "", "removed_info": ""}, {"lesson": "7", "group": "PD4", "room": "D14", "subject": "PRA", "subject_text": "Praxe", "teacher": "Vd", "teacher_text": "Mgr. Michal Vondrášek", "change_info": "", "theme": "Výroba zívitů", "type": "atom", "absencetext": "", "has_absent": "false", "absent_info_text": "", "removed_info": ""}], "41": [{"lesson": "8", "group": "PD1", "room": "D13", "subject": "PRA", "subject_text": "Praxe", "teacher": "Sr", "teacher_text": "Stanislav Stropek", "change_info": "", "theme": "Frézování šikmých ploch", "type": "atom", "absencetext": "", "has_absent": "false", "absent_info_text": "", "removed_info": ""}, {"lesson": "8", "group": "PD2", "room": "D16", "subject": "PRA", "subject_text": "Praxe", "teacher": "La", "teacher_text": "Mgr. Ivan Lavička", "change_info": "", "theme": "Metoda 111 (MMA) - BOZP, svařovací zdroje, přídavné materiály, parametry, příprava materiálu před svařováním a polohy", "type": "atom", "absencetext": "", "has_absent": "false", "absent_info_text": "", "removed_info": ""}, {"lesson": "8", "group": "PD3", "room": "D25", "subject": "PRA", "subject_text": "Praxe", "teacher": "Ra", "teacher_text": "Petr Rákos", "change_info": "", "theme": "Zásuvky 230V zapojení", "type": "atom", "absencetext": "", "has_absent": "false", "absent_info_text": "", "removed_info": ""}, {"lesson": "8", "group": "PD4", "room": "D14", "subject": "PRA", "subject_text": "Praxe", "teacher": "Vd", "teacher_text": "Mgr. Michal Vondrášek", "change_info": "", "theme": "Výroba zívitů", "type": "atom", "absencetext": "", "has_absent": "false", "absent_info_text": "", "removed_info": ""}], "44": [{"lesson": "0", "group": "", "room": "23", "subject": "ZSV", "subject_text": "Základy společenských věd", "teacher": "Šu", "teacher_text": "Mgr. Pavlína Šustrová", "change_info": "", "theme": "Velmoci, vyspělé státy, rozvojové země a jejich problémy", "type": "atom", "absencetext": "", "has_absent": "false", "absent_info_text": "", "removed_info": ""}], "45": [{"lesson": "1", "group": "", "room": "23", "subject": "ST", "subject_text": "Strojírenská technologie", "teacher": "Vd", "teacher_text": "Mgr. Michal Vondrášek", "change_info": "", "theme": "Opakování-test+pájení", "type": "atom", "absencetext": "", "has_absent": "false", "absent_info_text": "", "removed_info": ""}], "46": [{"lesson": "2", "group": "", "room": "23", "subject": "ST", "subject_text": "Strojírenská technologie", "teacher": "Vd", "teacher_text": "Mgr. Michal Vondrášek", "change_info": "", "theme": "Dělelní materiálu", "type": "atom", "absencetext": "", "has_absent": "false", "absent_info_text": "", "removed_info": ""}], "47": [{"lesson": "3", "group": "", "room": "23", "subject": "MA", "subject_text": "Matematika", "teacher": "Ml", "teacher_text": "Mgr. Michaela Malíková", "change_info": "", "theme": "Objemy a povrchy těles", "type": "atom", "absencetext": "", "has_absent": "false", "absent_info_text": "", "removed_info": ""}], "48": [{"lesson": "4", "group": "", "room": "23", "subject": "FY", "subject_text": "Fyzika", "teacher": "Pl", "teacher_text": "Mgr. Jiří Ploch", "change_info": "", "theme": "Test", "type": "atom", "absencetext": "", "has_absent": "false", "absent_info_text": "", "removed_info": ""}], "49": [{"lesson": "5", "group": "", "room": "25", "subject": "ME", "subject_text": "Mechanika", "teacher": "Kp", "teacher_text": "Ing. Petr Kroupa", "change_info": "", "theme": "Shrnutí látky - pružnost pevnost. Opakování před písemným testem.", "type": "atom", "absencetext": "", "has_absent": "false", "absent_info_text": "", "removed_info": ""}]}