{"4":[{"lesson":null,"group":"1.EM P4","room":"D6","subject":null,"subject_text":"Praxe | st  | 4 (10:45 - 11:30)","teacher":"Stanislav Stropek","teacher_text":null,"change_info":"","theme":"","type":"atom","absencetext":null,"has_absent":"false","absent_info_text":"","removed_info":""}],"5":[{"lesson":null,"group":"1.EM P4","room":"D6","subject":null,"subject_text":"Praxe | st  | 5 (11:40 - 12:25)","teacher":"Stanislav Stropek","teacher_text":null,"change_info":"","theme":"","type":"atom","absencetext":null,"has_absent":"false","absent_info_text":"","removed_info":""}],"6":[{"lesson":null,"group":"1.EM P4","room":"D6","subject":null,"subject_text":"Praxe | st  | 6 (12:30 - 13:15)","teacher":"Stanislav Stropek","teacher_text":null,"change_info":"","theme":"","type":"atom","absencetext":null,"has_absent":"false","absent_info_text":"","removed_info":""}]}