{"1":[{"lesson":"1","group":"4.EB celá","room":"47","subject":"EZ","subject_text":"Elektrická zařízení","teacher":"","teacher_text":"","change_info":"","theme":"","type":"atom","absencetext":null,"has_absent":"false","absent_info_text":"","removed_info":""}],"3":[{"lesson":"3","group":"2.EE celá","room":"50","subject":"EG","subject_text":"Elektrotechnologie","teacher":"","teacher_text":"","change_info":"","theme":"","type":"atom","absencetext":null,"has_absent":"false","absent_info_text":"","removed_info":""}],"4":[{"lesson":"4","group":"2.EE celá","room":"50","subject":"ZE","subject_text":"Základy elektrotechniky","teacher":"","teacher_text":"","change_info":"","theme":"","type":"atom","absencetext":null,"has_absent":"false","absent_info_text":"","removed_info":""}],"8":[{"lesson":"8","group":"3.EB celá","room":"43","subject":"EE","subject_text":"Elektroenergetika","teacher":"","teacher_text":"","change_info":"","theme":"","type":"atom","absencetext":null,"has_absent":"false","absent_info_text":"","removed_info":""}],"11":[{"lesson":"0","group":"2.ER 2","room":"28","subject":"L: ZEc","subject_text":"Základy elektrotechniky-cvičení","teacher":"","teacher_text":"","change_info":"","theme":"","type":"atom","absencetext":null,"has_absent":"false","absent_info_text":"","removed_info":""},{"lesson":"0","group":"2.ER 1","room":"28","subject":"S: ZEc","subject_text":"Základy elektrotechniky-cvičení","teacher":"","teacher_text":"","change_info":"","theme":"","type":"atom","absencetext":null,"has_absent":"false","absent_info_text":"","removed_info":""}],"12":[{"lesson":"1","group":"2.ER 2","room":"28","subject":"L: ZEc","subject_text":"Základy elektrotechniky-cvičení","teacher":"","teacher_text":"","change_info":"","theme":"","type":"atom","absencetext":null,"has_absent":"false","absent_info_text":"","removed_info":""},{"lesson":"1","group":"2.ER 1","room":"28","subject":"S: ZEc","subject_text":"Základy elektrotechniky-cvičení","teacher":"","teacher_text":"","change_info":"","theme":"","type":"atom","absencetext":null,"has_absent":"false","absent_info_text":"","removed_info":""}],"13":[{"lesson":"2","group":"4.EB celá","room":"47","subject":"EE","subject_text":"Elektroenergetika","teacher":"","teacher_text":"","change_info":"","theme":"","type":"atom","absencetext":null,"has_absent":"false","absent_info_text":"","removed_info":""}],"14":[{"lesson":"3","group":"2.ER celá","room":"34","subject":"ZE","subject_text":"Základy elektrotechniky","teacher":"","teacher_text":"","change_info":"","theme":"","type":"atom","absencetext":null,"has_absent":"false","absent_info_text":"","removed_info":""}],"17":[{"lesson":"6","group":"3.EB celá","room":"43","subject":"EE","subject_text":"Elektroenergetika","teacher":"","teacher_text":"","change_info":"","theme":"","type":"atom","absencetext":null,"has_absent":"false","absent_info_text":"","removed_info":""}],"23":[{"lesson":"1","group":"4.EB celá","room":"47","subject":"EE","subject_text":"Elektroenergetika","teacher":"","teacher_text":"","change_info":"","theme":"","type":"atom","absencetext":null,"has_absent":"false","absent_info_text":"","removed_info":""}],"33":[{"lesson":"0","group":"2.EE 1","room":"28","subject":"L: ZEc","subject_text":"Základy elektrotechniky-cvičení","teacher":"","teacher_text":"","change_info":"","theme":"","type":"atom","absencetext":null,"has_absent":"false","absent_info_text":"","removed_info":""},{"lesson":"0","group":"2.EE 2","room":"28","subject":"S: ZEc","subject_text":"Základy elektrotechniky-cvičení","teacher":"","teacher_text":"","change_info":"","theme":"","type":"atom","absencetext":null,"has_absent":"false","absent_info_text":"","removed_info":""}],"34":[{"lesson":"1","group":"2.EE 1","room":"28","subject":"L: ZEc","subject_text":"Základy elektrotechniky-cvičení","teacher":"","teacher_text":"","change_info":"","theme":"","type":"atom","absencetext":null,"has_absent":"false","absent_info_text":"","removed_info":""},{"lesson":"1","group":"2.EE 2","room":"28","subject":"S: ZEc","subject_text":"Základy elektrotechniky-cvičení","teacher":"","teacher_text":"","change_info":"","theme":"","type":"atom","absencetext":null,"has_absent":"false","absent_info_text":"","removed_info":""}],"35":[{"lesson":"2","group":"4.EB celá","room":"47","subject":"EZ","subject_text":"Elektrická zařízení","teacher":"","teacher_text":"","change_info":"","theme":"","type":"atom","absencetext":null,"has_absent":"false","absent_info_text":"","removed_info":""}],"37":[{"lesson":"4","group":"4.EB celá","room":"47","subject":"EE","subject_text":"Elektroenergetika","teacher":"","teacher_text":"","change_info":"","theme":"","type":"atom","absencetext":null,"has_absent":"false","absent_info_text":"","removed_info":""}],"38":[{"lesson":"5","group":"4.EB 2","room":"75","subject":"L: EEc","subject_text":"Elektroenergetika cvičení","teacher":"","teacher_text":"","change_info":"","theme":"","type":"atom","absencetext":null,"has_absent":"false","absent_info_text":"","removed_info":""},{"lesson":"5","group":"4.EB 1","room":"75","subject":"S: EEc","subject_text":"Elektroenergetika cvičení","teacher":"","teacher_text":"","change_info":"","theme":"","type":"atom","absencetext":null,"has_absent":"false","absent_info_text":"","removed_info":""}],"39":[{"lesson":"6","group":"4.EB 2","room":"75","subject":"L: EEc","subject_text":"Elektroenergetika cvičení","teacher":"","teacher_text":"","change_info":"","theme":"","type":"atom","absencetext":null,"has_absent":"false","absent_info_text":"","removed_info":""},{"lesson":"6","group":"4.EB 1","room":"75","subject":"S: EEc","subject_text":"Elektroenergetika cvičení","teacher":"","teacher_text":"","change_info":"","theme":"","type":"atom","absencetext":null,"has_absent":"false","absent_info_text":"","removed_info":""}],"45":[{"lesson":"1","group":"2.ER celá","room":"34","subject":"EG","subject_text":"Elektrotechnologie","teacher":"","teacher_text":"","change_info":"","theme":"","type":"atom","absencetext":null,"has_absent":"false","absent_info_text":"","removed_info":""}],"47":[{"lesson":"3","group":"2.EE celá","room":"50","subject":"ZE","subject_text":"Základy elektrotechniky","teacher":"","teacher_text":"","change_info":"","theme":"","type":"atom","absencetext":null,"has_absent":"false","absent_info_text":"","removed_info":""}],"48":[{"lesson":"4","group":"2.ER celá","room":"34","subject":"ZE","subject_text":"Základy elektrotechniky","teacher":"","teacher_text":"","change_info":"","theme":"","type":"atom","absencetext":null,"has_absent":"false","absent_info_text":"","removed_info":""}]}